tradingapi/__init__.py
tradingapi/broker_base.py
tradingapi/config.py
tradingapi/error_handling.py
tradingapi/exceptions.py
tradingapi/fivepaisa.py
tradingapi/flattrade.py
tradingapi/globals.py
tradingapi/icicidirect.py
tradingapi/shoonya.py
tradingapi/testing.py
tradingapi/utils.py
tradingapi-0.1.6.dist-info/METADATA
tradingapi-0.1.6.dist-info/WHEEL
tradingapi-0.1.6.dist-info/top_level.txt
tradingapi-0.1.6.dist-info/RECORD
