Metadata-Version: 2.4
Name: tradingapi
Version: 0.1.6
Summary: Trade integration with brokers
Author-email: Pankaj Sharma <sharma.pankaj.kumar@gmail.com>
License-Expression: MIT
Project-URL: homepage, https://bitbucket.org/incurrency/tradingpapi2
Project-URL: repository, https://bitbucket.org/incurrency/tradingapi2
Requires-Dist: chameli
Requires-Dist: NorenRestApi==0.0.32
Requires-Dist: py5paisa==0.7.20
Requires-Dist: redis==7.1.0
Requires-Dist: pyotp==2.9.0
Requires-Dist: httpx<0.29.0,>=0.25.0
Requires-Dist: bcrypt<4.0.0
